snapshotbackup/__init__.py
snapshotbackup/config.py
snapshotbackup/exceptions.py
snapshotbackup/subprocess.py
snapshotbackup/timestamps.py
snapshotbackup/volume.py
snapshotbackup/worker.py
snapshotbackup-0.0.19.dist-info/licenses/LICENSE
snapshotbackup-0.0.19.dist-info/METADATA
snapshotbackup-0.0.19.dist-info/WHEEL
snapshotbackup-0.0.19.dist-info/entry_points.txt
snapshotbackup-0.0.19.dist-info/top_level.txt
snapshotbackup-0.0.19.dist-info/RECORD
