Metadata-Version: 2.4
Name: snapshotbackup
Version: 0.0.19
Summary: backups with `rsync` and `btrfs` snapshots
Home-page: https://github.com/hbschr/snapshotbackup
Author: heiko huebscher
Author-email: heiko.huebscher@gmail.com
License: MIT
Keywords: backup cli commandline
Classifier: Development Status :: 3 - Alpha
Classifier: Environment :: Console
Classifier: Intended Audience :: Developers
Classifier: Topic :: System :: Archiving :: Backup
Classifier: License :: OSI Approved :: MIT License
Classifier: Programming Language :: Python :: 3.13
License-File: LICENSE
Requires-Dist: argcomplete>=1.11.1
Requires-Dist: dateparser>=1.2.2
Requires-Dist: humanfriendly>=10.0
Requires-Dist: psutil>=7.2.2
Requires-Dist: python-dateutil>=2.9.0.post0
Requires-Dist: xdg>=6.0.0
Provides-Extra: dev
Requires-Dist: coverage>=7.13.2; extra == "dev"
Requires-Dist: flake8>=7.3.0; extra == "dev"
Requires-Dist: pytest>=9.0.2; extra == "dev"
Requires-Dist: pytest-cov>=7.0.0; extra == "dev"
Requires-Dist: pytest-mccabe>=2.0; extra == "dev"
Requires-Dist: sphinx>=2.0.1; extra == "dev"
Requires-Dist: tox>=4.34.1; extra == "dev"
Provides-Extra: journald
Requires-Dist: systemd-python>=235; extra == "journald"
Dynamic: author
Dynamic: author-email
Dynamic: classifier
Dynamic: description
Dynamic: description-content-type
Dynamic: home-page
Dynamic: keywords
Dynamic: license
Dynamic: license-file
Dynamic: provides-extra
Dynamic: requires-dist
Dynamic: summary
